README.rst
setup.py
jetpackid/__init__.py
jetpackid/jetpackid.py
pyJetpackID.egg-info/PKG-INFO
pyJetpackID.egg-info/SOURCES.txt
pyJetpackID.egg-info/dependency_links.txt
pyJetpackID.egg-info/not-zip-safe
pyJetpackID.egg-info/top_level.txt