Metadata-Version: 1.0
Name: pyJetpackID
Version: 0.0.2
Summary: Takes the Jetpack add-on manifest object, and returns the add-on ID.
Home-page: https://github.com/askeing/pyJetpackID
Author: Askeing Yen
Author-email: askeing@gmail.com
License: UNKNOWN
Keywords: mozilla firefox jetpack jpm addon extension utilities
Platform: UNKNOWN
